CHANGELOG.md
CONTRIBUTING.md
LICENSE
MANIFEST.in
README.md
setup.cfg
setup.py
versioneer.py
src/siliqua/__init__.py
src/siliqua/_version.py
src/siliqua/cli.py
src/siliqua/config.py
src/siliqua/exceptions.py
src/siliqua/logger.py
src/siliqua/plugins.py
src/siliqua/server.py
src/siliqua/util.py
src/siliqua.egg-info/PKG-INFO
src/siliqua.egg-info/SOURCES.txt
src/siliqua.egg-info/dependency_links.txt
src/siliqua.egg-info/entry_points.txt
src/siliqua.egg-info/requires.txt
src/siliqua.egg-info/top_level.txt
src/siliqua/network/__init__.py
src/siliqua/network/exceptions.py
src/siliqua/network/nano_node/__init__.py
src/siliqua/network/nano_node/base.py
src/siliqua/network/nano_node/rpc.py
src/siliqua/network/nano_node/ws.py
src/siliqua/network/nanovault/__init__.py
src/siliqua/network/nanovault/rpc.py
src/siliqua/network/nanovault/ws.py
src/siliqua/ui/__init__.py
src/siliqua/ui/stdio/__init__.py
src/siliqua/ui/stdio/commands.py
src/siliqua/ui/stdio/exceptions.py
src/siliqua/ui/stdio/params.py
src/siliqua/ui/stdio/util.py
src/siliqua/wallet/__init__.py
src/siliqua/wallet/accounts.py
src/siliqua/wallet/exceptions.py
src/siliqua/wallet/secret.py
src/siliqua/wallet/util.py
src/siliqua/wallet/wallet.py
src/siliqua/work/__init__.py
src/siliqua/work/local.py