Metadata-Version: 2.1
Name: siliqua
Version: 0.1
Summary: Modular light wallet for the NANO cryptocurrency
Home-page: https://github.com/Matoking/siliqua
Author: Janne Pulkkinen
Author-email: jannepulk@gmail.com
License: CC0
Platform: UNKNOWN
Classifier: Programming Language :: Python
Classifier: Programming Language :: Python :: 3
Classifier: Programming Language :: Python :: 3.6
Classifier: Programming Language :: Python :: 3.7
Classifier: Programming Language :: Python :: Implementation :: CPython
Classifier: Operating System :: Microsoft :: Windows
Classifier: Operating System :: POSIX :: Linux
Classifier: Topic :: Office/Business :: Financial
Requires-Python: >=3.6.0
Provides-Extra: sphinx
